bopytex/__init__.py
bopytex/bopytex.py
bopytex/default_config.py
bopytex/jinja2_env/texenv.py
bopytex/message.py
bopytex/planner/__init__.py
bopytex/planner/activate_corr_compile_join_planner.py
bopytex/planner/exceptions.py
bopytex/planner/fake_planner.py
bopytex/planner/generate_compile_join_planner.py
bopytex/planner/naming.py
bopytex/scheduler.py
bopytex/script.py
bopytex/service.py
bopytex/tasks.py
bopytex/worker/__init__.py
bopytex/worker/activate_corr.py
bopytex/worker/clean.py
bopytex/worker/compile.py
bopytex/worker/generate.py
bopytex/worker/join_pdf.py
bopytex-1.0.0rc1.dist-info/WHEEL
bopytex-1.0.0rc1.dist-info/METADATA
bopytex-1.0.0rc1.dist-info/RECORD
