Metadata-Version: 2.1
Name: bopytex
Version: 1.0.0rc1
Summary: Command line tool for compiling latex with python command embedded
License: GPLv3
Author: Bertrand Benjamin
Author-email: benjamin.bertrand@opytex.org
Requires-Python: >=3.10,<4.0
Classifier: License :: Other/Proprietary License
Classifier: Programming Language :: Python :: 3
Classifier: Programming Language :: Python :: 3.10
Requires-Dist: Jinja2 (>=3.1.2,<4.0.0)
Requires-Dist: click (>=8.1.3,<9.0.0)
